pyopenwatch/__init__.py
pyopenwatch/ethereum_classes.py
pyopenwatch/ethereum_exceptions.py
pyopenwatch/ethereum_nft_watcher.py
pyopenwatch/ethereum_utility.py
pyOpENWatch-1.2.3.dist-info/LICENSE
pyOpENWatch-1.2.3.dist-info/METADATA
pyOpENWatch-1.2.3.dist-info/WHEEL
pyOpENWatch-1.2.3.dist-info/top_level.txt
pyOpENWatch-1.2.3.dist-info/RECORD
