Metadata-Version: 2.1
Name: pyOpENWatch
Version: 1.2.3
Summary: Fetch NFTs that were minted in the blockchain 
Home-page: https://github.com/ArtShield/pyOpENWatch
Author: Ege Emir Ozkan
Author-email: egeemirozkan24@gmail.com
License: MIT
Platform: UNKNOWN
Classifier: License :: OSI Approved :: GNU General Public License v3 (GPLv3)
Classifier: Programming Language :: Python :: 3
Classifier: Programming Language :: Python :: 3.10
License-File: LICENSE
Requires-Dist: requests
